hydrophis-1.0.1.dist-info/DESCRIPTION.rst
hydrophis-1.0.1.dist-info/METADATA
hydrophis-1.0.1.dist-info/RECORD
hydrophis-1.0.1.dist-info/WHEEL
hydrophis-1.0.1.dist-info/metadata.json
hydrophis-1.0.1.dist-info/top_level.txt
zbb_crawler/__init__.py
zbb_crawler/main.py
