Metadata-Version: 2.0
Name: hydrophis
Version: 1.0.1
Summary: python general crawler
Home-page: https://github.com/dpcrarchydrophis/hydrophis.git
Author: dpcrarchydrophis
Author-email: dpcrarchydrophis@gmail.com
License: meituan
Platform: UNKNOWN
Requires-Dist: Twisted (==17.1.0)
Requires-Dist: beautifulsoup4
Requires-Dist: boto (==2.47.0)
Requires-Dist: boto (>=2.47.0)
Requires-Dist: futures (==3.1.1)
Requires-Dist: gevent
Requires-Dist: incremental (==16.10.1)
Requires-Dist: lxml (==4.0.0)
Requires-Dist: nose
Requires-Dist: pybloom
Requires-Dist: requests (==2.13.0)
